handsonmachinelearn/NN.py
handsonmachinelearn/__init__
handsonmachinelearn/classification.py
handsonmachinelearn/eFS.py
handsonmachinelearn/ensemble.py
handsonmachinelearn/fuzzy.py
handsonmachinelearn/genetic.py
handsonmachinelearn/kernel.py
handsonmachinelearn/krls.py
handsonmachinelearn-0.0.9.dist-info/METADATA
handsonmachinelearn-0.0.9.dist-info/WHEEL
handsonmachinelearn-0.0.9.dist-info/licenses/LICENSE
handsonmachinelearn-0.0.9.dist-info/RECORD
