Metadata-Version: 2.4
Name: handsonmachinelearn
Version: 0.0.9
Summary: handsonmachinelearn (machine learning models)
Project-URL: Homepage, https://github.com/kaikerochaalves/handsonmachinelearn.git
Project-URL: Issues, https://github.com/kaikerochaalves/handsonmachinelearn.git
Author-email: Kaike Sa Teles Rocha Alves <kaikerochaalves@outlook.com>
License-File: LICENSE
Classifier: License :: OSI Approved :: GNU General Public License v3 (GPLv3)
Classifier: Programming Language :: Python :: 3
Requires-Python: >=3.0
Requires-Dist: matplotlib
Requires-Dist: numpy
Requires-Dist: pandas
Requires-Dist: pygad
Requires-Dist: scikit-learn
Requires-Dist: scipy
Requires-Dist: torch
Requires-Dist: torchaudio
Requires-Dist: torchvision
Requires-Dist: tqdm
